DDS/Assignment_3/6. 4-bit adder_subtractor/add_sub.v
`timescale 1ns/1ns


module Half_Adder (
    input in_a, in_b,
    output sum, carry
);
    
    xor(sum, in_a, in_b);
    and(carry, in_a, in_b);

endmodule

module Full_Adder (
    input in_a, in_b, in_c,
    output sum, carry 
);
    wire x,y,z;
    Half_Adder h1(
        .in_a(in_a),
        .in_b(in_b),
        .sum(x),
        .carry(y)
    );

    Half_Adder h2(
        .in_a(x),
        .in_b(in_c),
        .sum(sum),
        .carry(z)
    );

    or(carry, z, y);

endmodule

module four_bit_tb;
    reg a4 = 1'b1, a3 = 1'b1, a2 = 1'b0, a1 = 1'b1;
    reg b4 = 1'b0, b3 = 1'b0, b2 = 1'b0, b1 = 1'b1;
    reg m = 1'b0;
    wire s1, s2, s3, s4;
    wire c1, c2, c3;

    Full_Adder f1(
        .in_a(a1),
        .in_b(b1),
        .in_c(m),
        .carry(c1),
        .sum(s1)
    );
    Full_Adder f2(
        .in_a(a2),
        .in_b(b2),
        .in_c(c1),
        .carry(c2),
        .sum(s2)
    );
    Full_Adder f3(
        .in_a(a3),
        .in_b(b3),
        .in_c(c2),
        .carry(c3),
        .sum(s3)
    );
    Full_Adder f4(
        .in_a(a4),
        .in_b(b4),
        .in_c(c3),
        .sum(s4)
    );


    initial
    begin
        $dumpfile("four_bit.vcd");
        $dumpvars(0, four_bit_tb);
    end

    initial
    begin
        a4 = 1'b0;
        a3 = 1'b1;
        a2 = 1'b0;
        a1 = 1'b1;
        b4 = 1'b1;
        b3 = 1'b1;
        b2 = 1'b1;
        b1 = 1'b1;

        #10;
        a4 = 1'b1;
        a3 = 1'b1;
        a2 = 1'b0;
        a1 = 1'b0;
        b4 = 1'b1;
        b3 = 1'b0;
        b2 = 1'b1;
        b1 = 1'b1;

        #10;
        a4 = 1'b0;
        a3 = 1'b0;
        a2 = 1'b1;
        a1 = 1'b0; 
        b4 = 1'b0;
        b3 = 1'b0;
        b2 = 1'b0;
        b1 = 1'b0;

        #10;
        a4 = 1'b0;
        a3 = 1'b1;
        a2 = 1'b1;
        a1 = 1'b1;   
        #10;
        a4 = 1'b1;
        a3 = 1'b0;
        a2 = 1'b0;
        a1 = 1'b0;
        #10;
        a4 = 1'b0;
        a3 = 1'b0;
        a2 = 1'b0;
        a1 = 1'b0;
        #10;
        a4 = 1'b1;
        a3 = 1'b0;
        a2 = 1'b1;
        a1 = 1'b1;
        #10;
        a4 = 1'b1;
        a3 = 1'b1;
        a2 = 1'b1;
        a1 = 1'b1;
        #10;
    end
    initial
    begin
        $monitor("%d%d%d%d + %d%d%d%d = %d%d%d%d",a4,a3,a2,a1,b4,b3,b2,b1,s4,s3,s2,s1);
    end

endmodule

DDS/Assignment_3/6. 4-bit adder_subtractor/four_bit.vcd
$date
	Sat Oct 12 23:27:17 2019
$end
$version
	Icarus Verilog
$end
$timescale
	1ns
$end
$scope module four_bit_tb $end
$var wire 1 ! s4 $end
$var wire 1 " s3 $end
$var wire 1 # s2 $end
$var wire 1 $ s1 $end
$var wire 1 % c3 $end
$var wire 1 & c2 $end
$var wire 1 ' c1 $end
$var reg 1 ( a1 $end
$var reg 1 ) a2 $end
$var reg 1 * a3 $end
$var reg 1 + a4 $end
$var reg 1 , b1 $end
$var reg 1 - b2 $end
$var reg 1 . b3 $end
$var reg 1 / b4 $end
$var reg 1 0 m $end
$scope module f1 $end
$var wire 1 ' carry $end
$var wire 1 ( in_a $end
$var wire 1 , in_b $end
$var wire 1 0 in_c $end
$var wire 1 1 z $end
$var wire 1 2 y $end
$var wire 1 3 x $end
$var wire 1 $ sum $end
$scope module h1 $end
$var wire 1 2 carry $end
$var wire 1 ( in_a $end
$var wire 1 , in_b $end
$var wire 1 3 sum $end
$upscope $end
$scope module h2 $end
$var wire 1 1 carry $end
$var wire 1 3 in_a $end
$var wire 1 0 in_b $end
$var wire 1 $ sum $end
$upscope $end
$upscope $end
$scope module f2 $end
$var wire 1 & carry $end
$var wire 1 ) in_a $end
$var wire 1 - in_b $end
$var wire 1 ' in_c $end
$var wire 1 4 z $end
$var wire 1 5 y $end
$var wire 1 6 x $end
$var wire 1 # sum $end
$scope module h1 $end
$var wire 1 5 carry $end
$var wire 1 ) in_a $end
$var wire 1 - in_b $end
$var wire 1 6 sum $end
$upscope $end
$scope module h2 $end
$var wire 1 4 carry $end
$var wire 1 6 in_a $end
$var wire 1 ' in_b $end
$var wire 1 # sum $end
$upscope $end
$upscope $end
$scope module f3 $end
$var wire 1 % carry $end
$var wire 1 * in_a $end
$var wire 1 . in_b $end
$var wire 1 & in_c $end
$var wire 1 7 z $end
$var wire 1 8 y $end
$var wire 1 9 x $end
$var wire 1 " sum $end
$scope module h1 $end
$var wire 1 8 carry $end
$var wire 1 * in_a $end
$var wire 1 . in_b $end
$var wire 1 9 sum $end
$upscope $end
$scope module h2 $end
$var wire 1 7 carry $end
$var wire 1 9 in_a $end
$var wire 1 & in_b $end
$var wire 1 " sum $end
$upscope $end
$upscope $end
$scope module f4 $end
$var wire 1 : carry $end
$var wire 1 + in_a $end
$var wire 1 / in_b $end
$var wire 1 % in_c $end
$var wire 1 ; z $end
$var wire 1 < y $end
$var wire 1 = x $end
$var wire 1 ! sum $end
$scope module h1 $end
$var wire 1 < carry $end
$var wire 1 + in_a $end
$var wire 1 / in_b $end
$var wire 1 = sum $end
$upscope $end
$scope module h2 $end
$var wire 1 ; carry $end
$var wire 1 = in_a $end
$var wire 1 % in_b $end
$var wire 1 ! sum $end
$upscope $end
$upscope $end
$upscope $end
$enddefinitions $end
#0
$dumpvars
1=
0<
1;
1:
09
18
07
16
05
14
03
12
01
00
1/
1.
1-
1,
0+
1*
0)
1(
1'
1&
1%
0$
0#
1"
0!
$end
#10
0&
1#
04
1"
07
0%
1$
0'
0!
0;
19
08
13
02
0=
1<
0.
0(
1+
#20
0$
0"
0:
03
09
0<
0,
0-
0/
1)
0*
0+
#30
1$
1"
13
19
1(
1*
#40
0$
0#
0"
1!
03
06
09
1=
0(
0)
0*
1+
#50
0!
0=
0+
#60
1$
1#
1!
13
16
1=
1(
1)
1+
#70
1"
19
1*
