DDS/Assignment_3/11. Code Converters/Excess-3 to BCD/Excess3toBCD.v
`timescale 1ns/1ns

module Excess3toBCD (a, b, c, d, w, x, y, z);
    input a, b, c, d;
    output w, x ,y ,z;
    wire e,f;

    and(e,c,d);
    or(f,b,e);
    and(w,a,f);

    xnor(x,b,e);

    not(z,d);

    xor(y,c,d);
    

endmodule 

module Excess3toBCD_tb;

    reg a = 1'b0;
    reg b = 1'b0;
    reg c = 1'b0;
    reg d = 1'b0;

    wire w, x, y, z;

    Excess3toBCD h1(a,b,c,d,w,x,y,z);

    initial
    begin
        $dumpfile("Excess3toBCD.vcd");
        $dumpvars(0, Excess3toBCD_tb);
    end

    initial
    begin
        a = 1'b0;
        b = 1'b0;
        c = 1'b1;
        d = 1'b1;
        #10;
        a = 1'b0;
        b = 1'b1;
        c = 1'b0;
        d = 1'b0;
        #10;
        a = 1'b0;
        b = 1'b1;
        c = 1'b0;
        d = 1'b1;
        #10;
        a = 1'b0;
        b = 1'b1;
        c = 1'b1;
        d = 1'b0;
        #10;
        a = 1'b0;
        b = 1'b1;
        c = 1'b1;
        d = 1'b1;
        #10;
        a = 1'b1;
        b = 1'b0;
        c = 1'b0;
        d = 1'b0;
        #10;
        a = 1'b1;
        b = 1'b0;
        c = 1'b0;
        d = 1'b1;
        #10;
        a = 1'b1;
        b = 1'b0;
        c = 1'b1;
        d = 1'b0;
        #10;
        a = 1'b1;
        b = 1'b0;
        c = 1'b1;
        d = 1'b1;
        #10;
        a = 1'b1;
        b = 1'b1;
        c = 1'b0;
        d = 1'b0;
        #10;
    end

    initial
    begin
        $monitor("A = %d\tB = %d\tC = %d\tD = %d\t\tW = %d\tX = %d\tY = %d\tZ = %d\t",a,b,c,d,w,x,y,z);
    end

endmodule

DDS/Assignment_3/11. Code Converters/Excess-3 to BCD/Excess3toBCD.vcd
$date
	Sun Oct 13 00:23:25 2019
$end
$version
	Icarus Verilog
$end
$timescale
	1ns
$end
$scope module Excess3toBCD_tb $end
$var wire 1 ! z $end
$var wire 1 " y $end
$var wire 1 # x $end
$var wire 1 $ w $end
$var reg 1 % a $end
$var reg 1 & b $end
$var reg 1 ' c $end
$var reg 1 ( d $end
$scope module h1 $end
$var wire 1 % a $end
$var wire 1 & b $end
$var wire 1 ' c $end
$var wire 1 ( d $end
$var wire 1 ) e $end
$var wire 1 * f $end
$var wire 1 $ w $end
$var wire 1 # x $end
$var wire 1 " y $end
$var wire 1 ! z $end
$upscope $end
$upscope $end
$enddefinitions $end
#0
$dumpvars
1*
1)
1(
1'
0&
0%
0$
0#
0"
0!
$end
#10
1!
0)
0#
0(
0'
1&
#20
0!
1"
1(
#30
1!
0(
1'
#40
1#
1)
0!
0"
1(
#50
0*
1!
0)
1#
0$
0(
0'
0&
1%
#60
0!
1"
1(
#70
1!
0(
1'
#80
1$
1*
0#
1)
0!
0"
1(
#90
1!
0)
0#
0(
0'
1&
