DDS/Assignment_3/13-Mux-Demux/mux.v
`timescale 1ns/1ns
module Mux_16_1
(
    input [3:0] s,
    input [31:0] a1,
    input [31:0] a2,
    input [31:0] a3,
    input [31:0] a4,
    input [31:0] a5,
    input [31:0] a6,
    input [31:0] a7,
    input [31:0] a8,
    input [31:0] a9,
    input [31:0] a10,
    input [31:0] a11,
    input [31:0] a12,
    input [31:0] a13,
    input [31:0] a14,
    input [31:0] a15,
    input [31:0] a16,
    output [31:0] X
);

    reg [31:0] A;
    always @(*)
    begin
/*
        case (s)
            4'b0000 : assign A = a1;
            4'b0001 : assign A = a2;
            4'b0010 : assign A = a3;
            4'b0011 : assign A = a4;
            4'b0100 : assign A = a5;
            4'b0101 : assign A = a6;
            4'b0110 : assign A = a7;
            4'b0111 : assign A = a8;
            4'b1000 : assign A = a9;
            4'b1001 : assign A = a10;
            4'b1010 : assign A = a11;
            4'b1011 : assign A = a12;
            4'b1100 : assign A = a13;
            4'b1101 : assign A = a14;
            4'b1110 : assign A = a15;
            4'b1111 : assign A = a16;
*/
        case (s)
            4'b0000 : A <= a1;
            4'b0001 : A <= a2;
            4'b0010 : A <= a3;
            4'b0011 : A <= a4;
            4'b0100 : A <= a5;
            4'b0101 : A <= a6;
            4'b0110 : A <= a7;
            4'b0111 : A <= a8;
            4'b1000 : A <= a9;
            4'b1001 : A <= a10;
            4'b1010 : A <= a11;
            4'b1011 : A <= a12;
            4'b1100 : A <= a13;
            4'b1101 : A <= a14;
            4'b1110 : A <= a15;
            4'b1111 : A <= a16;
        endcase
    end

    assign X = A;

endmodule

module mux_tb;
    reg [31:0] a1;
    reg [31:0] a2;
    reg [31:0] a3;
    reg [31:0] a4;
    reg [31:0] a5;
    reg [31:0] a6;
    reg [31:0] a7;
    reg [31:0] a8;
    reg [31:0] a9;
    reg [31:0] a10;
    reg [31:0] a11;
    reg [31:0] a12;
    reg [31:0] a13;
    reg [31:0] a14;
    reg [31:0] a15;
    reg [31:0] a16;
    reg [3:0] s;
    wire [31:0] answer;

    Mux_16_1 M
    (
        .s(s),
        .a1(a1),
        .a2(a2),
        .a3(a3),
        .a4(a4),
        .a5(a5),
        .a6(a6),
        .a7(a7),
        .a8(a8),
        .a9(a9),
        .a10(a10),
        .a11(a11),
        .a12(a12),
        .a13(a13),
        .a14(a14),
        .a15(a15),
        .a16(a16),
        .X(answer)
    );

    initial
    begin
        $dumpfile("MUX.vcd");
        $dumpvars(0, mux_tb);
    end

    initial
    begin
        s = 4'b0010;
        a1 = 32'b00001100000001111101001011100100;
        a2 = 32'b11000111101011001000011101011101;
        a3 = 32'b00000101110100001101101111100110;
        a4 = 32'b01110100100100110001000100000111;
        a5 = 32'b01101110001110110100010010110111;
        a6 = 32'b01011110100010010011001101010011;
        a7 = 32'b01000101011001100110101110111000;
        a8 = 32'b00001000011001010110100001010000;
        a9 = 32'b11011001110100100001010010111100;
        a10 = 32'b01011110110000000011111011011110;
        a11 = 32'b01111000111011000000101100110000;
        a12 = 32'b00000110000100101001100111000110;
        a13 = 32'b00101111111100100100111010011010;
        a14 = 32'b00110100110100000010001110111110;
        a15 = 32'b01000011000000100100011101101000;
        a16 = 32'b11010111101001010111110100001011;
        #100;

        s = 4'b1001;
        a1 = 32'b10110011011000101101000111110111;
        a2 = 32'b10100011110010101011101011111110;
        a3 = 32'b10101001011010100010000101110111;
        a4 = 32'b11001000010101001011011101011101;
        a5 = 32'b01001001000001110001101100110101;
        a6 = 32'b01010101010000001111011000011011;
        a7 = 32'b00101101000101001000100100011111;
        a8 = 32'b00100101001011001100011010010011;
        a9 = 32'b11111101010000010101110010111101;
        a10 = 32'b01011110110000000011111011011110;
        a11 = 32'b01011111011110010011000010100110;
        a12 = 32'b10111111100111110110101100010010;
        a13 = 32'b00000111111110101110110111000101;
        a14 = 32'b00110100110100000010001110111110;
        a15 = 32'b01000011000000100100011101101000;
        a16 = 32'b11111111011111011100001101010110;
        #100;

        s = 4'b0101;
        a1 = 32'b00010001111001110000111100100010;
        a2 = 32'b00101011100100101101000011011101;
        a3 = 32'b01101001111111110110101111001011;
        a4 = 32'b11110110000110011101101101011101;
        a5 = 32'b10110110111111111100010110101001;
        a6 = 32'b10111000011110000000111100011000;
        a7 = 32'b00001111101101011101010001011110;
        a8 = 32'b11101000111100001010100000000010;
        a9 = 32'b01110001100011010110001000010110;
        a10 = 32'b01001000011001011000111111100100;
        a11 = 32'b00001000011100011111000110111000;
        a12 = 32'b01001010110011100101101110101111;
        a13 = 32'b01101101101001001011011000100100;
        a14 = 32'b11011010001000001101010010010001;
        a15 = 32'b11000001110000011110000000110001;
        a16 = 32'b00100101100101001100110000100101;
        #100;

        s = 4'b1010;
        a1 = 32'b11011011001111000110000010011101;
        a2 = 32'b10001001110000010000010011100111;
        a3 = 32'b01100000011010000010011000110111;
        a4 = 32'b10010111101000010111001100011110;
        a5 = 32'b01011000011101011110100001010011;
        a6 = 32'b01110001001001101010001110011100;
        a7 = 32'b10101111110111010010111100111110;
        a8 = 32'b00111000000110111100111001110111;
        a9 = 32'b11001001001111010110111101111110;
        a10 = 32'b00101111011010100011001100111010;
        a11 = 32'b00000110010000001111101110100111;
        a12 = 32'b10111011100100100110001100110010;
        a13 = 32'b00010010000110111010001010000010;
        a14 = 32'b01001101010101110110010101100111;
        a15 = 32'b01101110001011110111100010010000;
        a16 = 32'b01101110100110000010011100010101;
        #100;

        s = 4'b0000;
        a1 = 32'b10000010110101000000000001000110;
        a2 = 32'b01111001101011101111110011110001;
        a3 = 32'b11001100100010100001011101000111;
        a4 = 32'b10100000010100011101000000001010;
        a5 = 32'b11100001100111110111011001001100;
        a6 = 32'b00001000001100110110100101101111;
        a7 = 32'b10010100011100011101001100001111;
        a8 = 32'b00111010110010101100010100111110;
        a9 = 32'b10111000000111011010111000100110;
        a10 = 32'b11111010100000011000000010001101;
        a11 = 32'b10101111111110110101101100101010;
        a12 = 32'b00001110010100100001111110011011;
        a13 = 32'b01000011110011011101001100010111;
        a14 = 32'b01010001001000010110101010111001;
        a15 = 32'b10011011101111111010010011110011;
        a16 = 32'b10010111010000111010111000101010;
        #100;
        
        s = 4'b1111;
        a1 = 32'b01100010001010001000001110101100;
        a2 = 32'b10000111011001011100111101111101;
        a3 = 32'b11001101100010011111110110011101;
        a4 = 32'b01101100100100000101101101111000;
        a5 = 32'b00001110001111000110010110010101;
        a6 = 32'b01111010110111101010001111001000;
        a7 = 32'b11001010100011101111100000001000;
        a8 = 32'b11001000100001010010100000101110;
        a9 = 32'b10011011011011010001001001010111;
        a10 = 32'b01111011100101010010110000011111;
        a11 = 32'b01001011100111101010100101110001;
        a12 = 32'b10100111100101100100000000000001;
        a13 = 32'b11110010100011110000100101000111;
        a14 = 32'b10010101000000101000101011011000;
        a15 = 32'b01000101011010011111001100110101;
        a16 = 32'b00101011001110001110000111011010;
        #100;

        s = 4'b1000;
        a1 = 32'b00111000000110110100011001110001;
        a2 = 32'b11011000100001000110110010110010;
        a3 = 32'b10101110010110000011011001101000;
        a4 = 32'b00111101000110100111010110001100;
        a5 = 32'b01101011110101001111001000000101;
        a6 = 32'b00111111101010101001001011100011;
        a7 = 32'b10000100001001101100111011010100;
        a8 = 32'b00011101100110111100101111000110;
        a9 = 32'b01000101100111110000101000001100;
        a10 = 32'b10111111000000100010101111111111;
        a11 = 32'b00010111000101111010000010000000;
        a12 = 32'b01110011100110110001011011000100;
        a13 = 32'b01100110010001000001011010101000;
        a14 = 32'b01010110111110111011110010001110;
        a15 = 32'b11110001000110100110011011010100;
        a16 = 32'b10000010110000001001010111000110;
        #100;

        s = 4'b1011;
        a1 = 32'b10111100110100001111100100011011;
        a2 = 32'b10111000110101110110000011111110;
        a3 = 32'b00100010110101101110001000101101;
        a4 = 32'b11000111100010111011110011100010;
        a5 = 32'b11000000111101010011111010101010;
        a6 = 32'b11010101011111110100000000010111;
        a7 = 32'b00001100111011111111100111010011;
        a8 = 32'b10011101001111001000000111101010;
        a9 = 32'b01001001100110101000011111110111;
        a10 = 32'b11001111101100110011110101111001;
        a11 = 32'b11001000110100100000100100100101;
        a12 = 32'b11001010010010101001110001011000;
        a13 = 32'b00011000010111111000010101100101;
        a14 = 32'b10110101010110111100000000011111;
        a15 = 32'b11001011101011101101001001111100;
        a16 = 32'b11001101100010111001110011011011;
        #100;
    end

    initial
    begin
        $monitor
        (
            "a1 = %b\na2 = %b\na3 = %b\na4 = %b\na5 = %b\na6 = %b\na7 = %b\na8 = %b\na9 = %b\na10 = %b\na11 = %b\na12 = %b\na13 = %b\na14 = %b\na15 = %b\na16 = %b\nselect = %b\nanswer = %b\n",
            a1,
            a2,
            a3,
            a4,
            a5,
            a6,
            a7,
            a8,
            a9,
            a10,
            a11,
            a12,
            a13,
            a14,
            a15,
            a16,
            s,
            answer
        );
    end

endmodule

DDS/Assignment_3/13-Mux-Demux/MUX.vcd
$date
	Sun Oct 13 10:16:11 2019
$end
$version
	Icarus Verilog
$end
$timescale
	1ns
$end
$scope module mux_tb $end
$var wire 32 ! answer [31:0] $end
$var reg 32 " a1 [31:0] $end
$var reg 32 # a10 [31:0] $end
$var reg 32 $ a11 [31:0] $end
$var reg 32 % a12 [31:0] $end
$var reg 32 & a13 [31:0] $end
$var reg 32 ' a14 [31:0] $end
$var reg 32 ( a15 [31:0] $end
$var reg 32 ) a16 [31:0] $end
$var reg 32 * a2 [31:0] $end
$var reg 32 + a3 [31:0] $end
$var reg 32 , a4 [31:0] $end
$var reg 32 - a5 [31:0] $end
$var reg 32 . a6 [31:0] $end
$var reg 32 / a7 [31:0] $end
$var reg 32 0 a8 [31:0] $end
$var reg 32 1 a9 [31:0] $end
$var reg 4 2 s [3:0] $end
$scope module M $end
$var wire 32 3 X [31:0] $end
$var wire 32 4 a1 [31:0] $end
$var wire 32 5 a10 [31:0] $end
$var wire 32 6 a11 [31:0] $end
$var wire 32 7 a12 [31:0] $end
$var wire 32 8 a13 [31:0] $end
$var wire 32 9 a14 [31:0] $end
$var wire 32 : a15 [31:0] $end
$var wire 32 ; a16 [31:0] $end
$var wire 32 < a2 [31:0] $end
$var wire 32 = a3 [31:0] $end
$var wire 32 > a4 [31:0] $end
$var wire 32 ? a5 [31:0] $end
$var wire 32 @ a6 [31:0] $end
$var wire 32 A a7 [31:0] $end
$var wire 32 B a8 [31:0] $end
$var wire 32 C a9 [31:0] $end
$var wire 4 D s [3:0] $end
$var reg 32 E A [31:0] $end
$upscope $end
$upscope $end
$enddefinitions $end
#0
$dumpvars
b101110100001101101111100110 E
b10 D
b11011001110100100001010010111100 C
b1000011001010110100001010000 B
b1000101011001100110101110111000 A
b1011110100010010011001101010011 @
b1101110001110110100010010110111 ?
b1110100100100110001000100000111 >
b101110100001101101111100110 =
b11000111101011001000011101011101 <
b11010111101001010111110100001011 ;
b1000011000000100100011101101000 :
b110100110100000010001110111110 9
b101111111100100100111010011010 8
b110000100101001100111000110 7
b1111000111011000000101100110000 6
b1011110110000000011111011011110 5
b1100000001111101001011100100 4
b101110100001101101111100110 3
b10 2
b11011001110100100001010010111100 1
b1000011001010110100001010000 0
b1000101011001100110101110111000 /
b1011110100010010011001101010011 .
b1101110001110110100010010110111 -
b1110100100100110001000100000111 ,
b101110100001101101111100110 +
b11000111101011001000011101011101 *
b11010111101001010111110100001011 )
b1000011000000100100011101101000 (
b110100110100000010001110111110 '
b101111111100100100111010011010 &
b110000100101001100111000110 %
b1111000111011000000101100110000 $
b1011110110000000011111011011110 #
b1100000001111101001011100100 "
b101110100001101101111100110 !
$end
#100
b1011110110000000011111011011110 !
b1011110110000000011111011011110 3
b1011110110000000011111011011110 E
b11111111011111011100001101010110 )
b11111111011111011100001101010110 ;
b111111110101110110111000101 &
b111111110101110110111000101 8
b10111111100111110110101100010010 %
b10111111100111110110101100010010 7
b1011111011110010011000010100110 $
b1011111011110010011000010100110 6
b11111101010000010101110010111101 1
b11111101010000010101110010111101 C
b100101001011001100011010010011 0
b100101001011001100011010010011 B
b101101000101001000100100011111 /
b101101000101001000100100011111 A
b1010101010000001111011000011011 .
b1010101010000001111011000011011 @
b1001001000001110001101100110101 -
b1001001000001110001101100110101 ?
b11001000010101001011011101011101 ,
b11001000010101001011011101011101 >
b10101001011010100010000101110111 +
b10101001011010100010000101110111 =
b10100011110010101011101011111110 *
b10100011110010101011101011111110 <
b10110011011000101101000111110111 "
b10110011011000101101000111110111 4
b1001 2
b1001 D
#200
b10111000011110000000111100011000 !
b10111000011110000000111100011000 3
b10111000011110000000111100011000 E
b100101100101001100110000100101 )
b100101100101001100110000100101 ;
b11000001110000011110000000110001 (
b11000001110000011110000000110001 :
b11011010001000001101010010010001 '
b11011010001000001101010010010001 9
b1101101101001001011011000100100 &
b1101101101001001011011000100100 8
b1001010110011100101101110101111 %
b1001010110011100101101110101111 7
b1000011100011111000110111000 $
b1000011100011111000110111000 6
b1001000011001011000111111100100 #
b1001000011001011000111111100100 5
b1110001100011010110001000010110 1
b1110001100011010110001000010110 C
b11101000111100001010100000000010 0
b11101000111100001010100000000010 B
b1111101101011101010001011110 /
b1111101101011101010001011110 A
b10111000011110000000111100011000 .
b10111000011110000000111100011000 @
b10110110111111111100010110101001 -
b10110110111111111100010110101001 ?
b11110110000110011101101101011101 ,
b11110110000110011101101101011101 >
b1101001111111110110101111001011 +
b1101001111111110110101111001011 =
b101011100100101101000011011101 *
b101011100100101101000011011101 <
b10001111001110000111100100010 "
b10001111001110000111100100010 4
b101 2
b101 D
#300
b110010000001111101110100111 !
b110010000001111101110100111 3
b110010000001111101110100111 E
b1101110100110000010011100010101 )
b1101110100110000010011100010101 ;
b1101110001011110111100010010000 (
b1101110001011110111100010010000 :
b1001101010101110110010101100111 '
b1001101010101110110010101100111 9
b10010000110111010001010000010 &
b10010000110111010001010000010 8
b10111011100100100110001100110010 %
b10111011100100100110001100110010 7
b110010000001111101110100111 $
b110010000001111101110100111 6
b101111011010100011001100111010 #
b101111011010100011001100111010 5
b11001001001111010110111101111110 1
b11001001001111010110111101111110 C
b111000000110111100111001110111 0
b111000000110111100111001110111 B
b10101111110111010010111100111110 /
b10101111110111010010111100111110 A
b1110001001001101010001110011100 .
b1110001001001101010001110011100 @
b1011000011101011110100001010011 -
b1011000011101011110100001010011 ?
b10010111101000010111001100011110 ,
b10010111101000010111001100011110 >
b1100000011010000010011000110111 +
b1100000011010000010011000110111 =
b10001001110000010000010011100111 *
b10001001110000010000010011100111 <
b11011011001111000110000010011101 "
b11011011001111000110000010011101 4
b1010 2
b1010 D
#400
b10000010110101000000000001000110 !
b10000010110101000000000001000110 3
b10000010110101000000000001000110 E
b10010111010000111010111000101010 )
b10010111010000111010111000101010 ;
b10011011101111111010010011110011 (
b10011011101111111010010011110011 :
b1010001001000010110101010111001 '
b1010001001000010110101010111001 9
b1000011110011011101001100010111 &
b1000011110011011101001100010111 8
b1110010100100001111110011011 %
b1110010100100001111110011011 7
b10101111111110110101101100101010 $
b10101111111110110101101100101010 6
b11111010100000011000000010001101 #
b11111010100000011000000010001101 5
b10111000000111011010111000100110 1
b10111000000111011010111000100110 C
b111010110010101100010100111110 0
b111010110010101100010100111110 B
b10010100011100011101001100001111 /
b10010100011100011101001100001111 A
b1000001100110110100101101111 .
b1000001100110110100101101111 @
b11100001100111110111011001001100 -
b11100001100111110111011001001100 ?
b10100000010100011101000000001010 ,
b10100000010100011101000000001010 >
b11001100100010100001011101000111 +
b11001100100010100001011101000111 =
b1111001101011101111110011110001 *
b1111001101011101111110011110001 <
b10000010110101000000000001000110 "
b10000010110101000000000001000110 4
b0 2
b0 D
#500
b101011001110001110000111011010 !
b101011001110001110000111011010 3
b101011001110001110000111011010 E
b101011001110001110000111011010 )
b101011001110001110000111011010 ;
b1000101011010011111001100110101 (
b1000101011010011111001100110101 :
b10010101000000101000101011011000 '
b10010101000000101000101011011000 9
b11110010100011110000100101000111 &
b11110010100011110000100101000111 8
b10100111100101100100000000000001 %
b10100111100101100100000000000001 7
b1001011100111101010100101110001 $
b1001011100111101010100101110001 6
b1111011100101010010110000011111 #
b1111011100101010010110000011111 5
b10011011011011010001001001010111 1
b10011011011011010001001001010111 C
b11001000100001010010100000101110 0
b11001000100001010010100000101110 B
b11001010100011101111100000001000 /
b11001010100011101111100000001000 A
b1111010110111101010001111001000 .
b1111010110111101010001111001000 @
b1110001111000110010110010101 -
b1110001111000110010110010101 ?
b1101100100100000101101101111000 ,
b1101100100100000101101101111000 >
b11001101100010011111110110011101 +
b11001101100010011111110110011101 =
b10000111011001011100111101111101 *
b10000111011001011100111101111101 <
b1100010001010001000001110101100 "
b1100010001010001000001110101100 4
b1111 2
b1111 D
#600
b1000101100111110000101000001100 !
b1000101100111110000101000001100 3
b1000101100111110000101000001100 E
b10000010110000001001010111000110 )
b10000010110000001001010111000110 ;
b11110001000110100110011011010100 (
b11110001000110100110011011010100 :
b1010110111110111011110010001110 '
b1010110111110111011110010001110 9
b1100110010001000001011010101000 &
b1100110010001000001011010101000 8
b1110011100110110001011011000100 %
b1110011100110110001011011000100 7
b10111000101111010000010000000 $
b10111000101111010000010000000 6
b10111111000000100010101111111111 #
b10111111000000100010101111111111 5
b1000101100111110000101000001100 1
b1000101100111110000101000001100 C
b11101100110111100101111000110 0
b11101100110111100101111000110 B
b10000100001001101100111011010100 /
b10000100001001101100111011010100 A
b111111101010101001001011100011 .
b111111101010101001001011100011 @
b1101011110101001111001000000101 -
b1101011110101001111001000000101 ?
b111101000110100111010110001100 ,
b111101000110100111010110001100 >
b10101110010110000011011001101000 +
b10101110010110000011011001101000 =
b11011000100001000110110010110010 *
b11011000100001000110110010110010 <
b111000000110110100011001110001 "
b111000000110110100011001110001 4
b1000 2
b1000 D
#700
b11001010010010101001110001011000 !
b11001010010010101001110001011000 3
b11001010010010101001110001011000 E
b11001101100010111001110011011011 )
b11001101100010111001110011011011 ;
b11001011101011101101001001111100 (
b11001011101011101101001001111100 :
b10110101010110111100000000011111 '
b10110101010110111100000000011111 9
b11000010111111000010101100101 &
b11000010111111000010101100101 8
b11001010010010101001110001011000 %
b11001010010010101001110001011000 7
b11001000110100100000100100100101 $
b11001000110100100000100100100101 6
b11001111101100110011110101111001 #
b11001111101100110011110101111001 5
b1001001100110101000011111110111 1
b1001001100110101000011111110111 C
b10011101001111001000000111101010 0
b10011101001111001000000111101010 B
b1100111011111111100111010011 /
b1100111011111111100111010011 A
b11010101011111110100000000010111 .
b11010101011111110100000000010111 @
b11000000111101010011111010101010 -
b11000000111101010011111010101010 ?
b11000111100010111011110011100010 ,
b11000111100010111011110011100010 >
b100010110101101110001000101101 +
b100010110101101110001000101101 =
b10111000110101110110000011111110 *
b10111000110101110110000011111110 <
b10111100110100001111100100011011 "
b10111100110100001111100100011011 4
b1011 2
b1011 D
