DDS/Assignment_5/Part1-ALU/alu1.v



//64 Bit alu


`timescale 1ns/1ns
module alu(a,b,operation,carry_in,Result,flag,carry_out);

      input [63:0] a;
      input [63:0] b;
	input [63:0] carry_in;
      input [3:0] operation;
      output [63:0]Result;
      output flag,carry_out;
      reg Result,flag,carry_out;

      always@(a or b or operation)
          begin
               case (operation)
                 4'b0000:  Result = a & b;   // AND
                 4'b0001:  Result = a | b;   // OR
                 4'b0010:  Result = a + b +carry_in;    // addition
                 4'b0110:  Result = a - b - carry_in;    // subtraction
		 4'b1101:  Result = !(a & b); //nand
		 4'b1100:  Result = !(a | b); //nor
               endcase

		begin
			if(operation[0]==0 && operation[1]==1 && operation[2]==0 && operation[3]==0)
			carry_out= a&b;
			else if(operation[0]==0 && operation[1]==1 && operation[2]==1 && operation[3]==0)
			carry_out= (~a)&b;
		end
		begin
			if(Result ==0 && carry_out==0)
			assign flag=1;
			else
			assign flag=0;
		end
           end 
		
endmodule	


module alu_tb;
	reg [63:0]a;
	reg [63:0]b;
	reg [63:0] carry_in;
	reg [3:0] operation;
	wire [63:0]Result;
	wire carry_out;

initial begin
	$dumpfile("alu1.vcd");
	$dumpvars(0,alu_tb);	
	$monitor ("a=%b, b=%b, operation=%b%b%b%b, carry_out=%b, Result=%b flag=%b ",a,b,operation[3],operation[2],operation[1],operation[0],carry_out,Result,flag);
	a=0;
	b=0;
	carry_in=0;
	operation[0]=0;
	operation[1]=0;
	operation[2]=0;
	operation[3]=0;
	
	#20 a=2;
	operation[0]=1;
	#20 b=3;
	#20 operation[0]=0;
	#20 operation[1]=1;
	#20 operation[2]=1;
	#20 a=1024;
	#20 operation[2]=0;
	carry_in=1;
	#20 operation[1]=1;
	#20 operation[3]=1;
	#20 b=120;
	#20 a=9;
	#20 operation[0]=1;

	#20 b=22;

	
	#10 $finish;
end

alu c(
	.a(a),
	.b(b),
	.operation(operation),
	.carry_in(carry_in),
	.Result(Result),
	.flag(flag),
	.carry_out(carry_out)
);
endmodule

DDS/Assignment_5/Part1-ALU/alu1.vcd
$date
	Fri Nov  8 20:13:23 2019
$end
$version
	Icarus Verilog
$end
$timescale
	1ns
$end
$scope module alu_tb $end
$var wire 1 ! flag $end
$var wire 1 " carry_out $end
$var wire 64 # Result [63:0] $end
$var reg 64 $ a [63:0] $end
$var reg 64 % b [63:0] $end
$var reg 64 & carry_in [63:0] $end
$var reg 4 ' operation [3:0] $end
$scope module c $end
$var wire 64 ( a [63:0] $end
$var wire 64 ) b [63:0] $end
$var wire 64 * carry_in [63:0] $end
$var wire 4 + operation [3:0] $end
$var reg 64 , Result [63:0] $end
$var reg 1 " carry_out $end
$var reg 1 ! flag $end
$upscope $end
$upscope $end
$enddefinitions $end
#0
$dumpvars
b0 ,
b0 +
b0 *
b0 )
b0 (
b0 '
b0 &
b0 %
b0 $
b0 #
x"
0!
$end
#20
b10 #
b10 ,
b1 '
b1 +
b10 $
b10 (
#40
b11 #
b11 ,
b11 %
b11 )
#60
b10 #
b10 ,
b0 '
b0 +
#80
0"
b101 #
b101 ,
b10 '
b10 +
#100
1"
b1111111111111111111111111111111111111111111111111111111111111111 #
b1111111111111111111111111111111111111111111111111111111111111111 ,
b110 '
b110 +
#120
b1111111101 #
b1111111101 ,
b10000000000 $
b10000000000 (
#140
0"
b10000000100 #
b10000000100 ,
b1 &
b1 *
b10 '
b10 +
#180
b1010 '
b1010 +
#200
b1111000 %
b1111000 )
#220
b1001 $
b1001 (
#240
b1011 '
b1011 +
#260
b10110 %
b10110 )
