DDS/Assignment_5/Part2-ALU/alureg.v
//Program:Implements a pipieline consisting of 64-Bit ALU and 32b x 64b register

module aluregfile(input clock,input reset,input[4:0]address1,input[4:0]address2,
            input[4:0]address3,input[4:0]address4,
            input[3:0]ALU_Sel,input en_write,
            input eval,input read,input[63:0]idata1,input[63:0]idata2,output reg[63:0]data);

// Register file storage
reg [63:0] registers[31:0];
reg [63:0] ALU_Result;

// Read and write from register file
always @(posedge clock)
    if(!reset) begin
        if (en_write==1 && eval==0 && read==0)
                begin
                registers[address1] <= idata1;
                registers[address2] <= idata2;
                end
        if(en_write==0 && eval==1 && read==0)
                begin
                    case(ALU_Sel)
                        4'b0000: // Addition
                        ALU_Result <= registers[address1] + registers[address2] ;
                        //ALU_Result <= idata1 + idata2 ; 
                        4'b0001: // Subtraction
                        ALU_Result <= registers[address1] - registers[address2] ;
                        4'b0010: // Multiplication
                        ALU_Result <= registers[address1] * registers[address2];
                        4'b0011: // Division
                        ALU_Result <= registers[address1]/registers[address2];
                        4'b0100: // Logical shift left
                        ALU_Result <= registers[address1]<<1;
                        4'b0101: // Logical shift right
                        ALU_Result <= registers[address1]>>1;
                        4'b0110: // Rotate left
                        ALU_Result <= {registers[address1][62:0],registers[address1][63]};
                        4'b0111: // Rotate right
                        ALU_Result <= {registers[address1][0],registers[address1][63:1]};
                        4'b1000: //  Logical and 
                        ALU_Result <= registers[address1] & registers[address2];
                        4'b1001: //  Logical or
                        ALU_Result <= registers[address1] | registers[address2];
                        4'b1010: //  Logical xor 
                        ALU_Result <= registers[address1] ^ registers[address2];
                        4'b1011: //  Logical nor
                        ALU_Result <= ~(registers[address1] | registers[address2]);
                        4'b1100: // Logical nand 
                        ALU_Result <= ~(registers[address1] & registers[address2]);
                        4'b1101: // Logical xnor
                        ALU_Result <= ~(registers[address1] ^ registers[address2]);
                        4'b1110: // Greater comparison
                        ALU_Result <= (registers[address1]>registers[address2])?8'd1:8'd0 ;
                        4'b1111: // Equal comparison   
                        ALU_Result <= (registers[address1]==registers[address2])?8'd1:8'd0 ;
                        default: ALU_Result = registers[address1] + registers[address2] ; 
                    endcase
                    registers[address3] <= ALU_Result;
                end
         if(read==1 && en_write==0 && eval==0)
                data <= registers[address4];
    end
endmodule

`timescale 1ns / 1ps
module stimulus;
    reg clock;
    reg reset;
    reg [4:0] address1;
    reg [4:0] address2;
    reg [4:0] address3;
    reg [4:0] address4;
    reg [3:0] ALU_Sel;
    reg en_write;
    reg eval;
    reg read;
    reg [63:0] idata1;
    reg [63:0] idata2;
    wire [63:0] data;

    aluregfile r1(
        .clock(clock),
        .reset(reset),
        .address1(address1),
        .address2(address2),
        .address3(address3),
        .address4(address4),
        .ALU_Sel(ALU_Sel),
        .en_write(en_write),
        .eval(eval),
        .read(read),
        .idata1(idata1),
        .idata2(idata2),
        .data(data)
    );

    integer i;
 
	initial begin
	$dumpfile("alureg.vcd");
    $dumpvars(0,stimulus);
    reset = 0;
	#5 en_write=1; eval=0; read=0; address1=1; idata1= 13456789; address2=8; idata2=456787;
	#10 en_write=0; eval=0; read=1; address4=1;
    #10 en_write=0; eval=0; read=1; address4=8; 
    #10
	#10 en_write=0; eval=1; read=0; ALU_Sel=4'b0000; address3=5;
    #20 en_write=0; eval=0; read=1; address4=5;
    #10 en_write=0; eval=1; read=0; ALU_Sel=4'b0001; address3=15;
    #20 en_write=0; eval=0; read=1; address4=15;
    #10 en_write=0; eval=1; read=0; ALU_Sel=4'b0010; address3=16;
    #20 en_write=0; eval=0; read=1; address4=16;
    #10 en_write=0; eval=1; read=0; ALU_Sel=4'b0011; address3=17;
    #20 en_write=0; eval=0; read=1; address4=17;
    #10 en_write=0; eval=1; read=0; ALU_Sel=4'b0100; address3=18;
    #20 en_write=0; eval=0; read=1; address4=18;
    #10 en_write=0; eval=1; read=0; ALU_Sel=4'b0101; address3=19;
    #20 en_write=0; eval=0; read=1; address4=19;
    #10 en_write=0; eval=1; read=0; ALU_Sel=4'b0110; address3=20;
    #20 en_write=0; eval=0; read=1; address4=20;
    #10 en_write=0; eval=1; read=0; ALU_Sel=4'b0111; address3=21;
    #20 en_write=0; eval=0; read=1; address4=21;
    #10 en_write=0; eval=1; read=0; ALU_Sel=4'b1000; address3=22;
    #20 en_write=0; eval=0; read=1; address4=22;
    #10 en_write=0; eval=1; read=0; ALU_Sel=4'b1001; address3=23;
    #20 en_write=0; eval=0; read=1; address4=23;
    #10 en_write=0; eval=1; read=0; ALU_Sel=4'b1010; address3=24;
    #20 en_write=0; eval=0; read=1; address4=24;
    #10 en_write=0; eval=1; read=0; ALU_Sel=4'b1011; address3=25;
    #20 en_write=0; eval=0; read=1; address4=25;
    #10 en_write=0; eval=1; read=0; ALU_Sel=4'b1100; address3=26;
    #20 en_write=0; eval=0; read=1; address4=26;
    #10 en_write=0; eval=1; read=0; ALU_Sel=4'b1101; address3=27;
    #20 en_write=0; eval=0; read=1; address4=27;
    #10 en_write=0; eval=1; read=0; ALU_Sel=4'b1110; address3=28;
    #20 en_write=0; eval=0; read=1; address4=28;
    #10 en_write=0; eval=1; read=0; ALU_Sel=4'b1111; address3=29;
    #20 en_write=0; eval=0; read=1; address4=29;
    end  
 
	initial begin
	clock = 0;
	for ( i =0; i <=100; i= i+1)
	#5 clock = ~clock;
    end  

endmodule

DDS/Assignment_5/Part2-ALU/alureg.vcd
$date
	Fri Nov  8 22:25:13 2019
$end
$version
	Icarus Verilog
$end
$timescale
	1ps
$end
$scope module stimulus $end
$var wire 64 ! data [63:0] $end
$var reg 4 " ALU_Sel [3:0] $end
$var reg 5 # address1 [4:0] $end
$var reg 5 $ address2 [4:0] $end
$var reg 5 % address3 [4:0] $end
$var reg 5 & address4 [4:0] $end
$var reg 1 ' clock $end
$var reg 1 ( en_write $end
$var reg 1 ) eval $end
$var reg 64 * idata1 [63:0] $end
$var reg 64 + idata2 [63:0] $end
$var reg 1 , read $end
$var reg 1 - reset $end
$var integer 32 . i [31:0] $end
$scope module r1 $end
$var wire 4 / ALU_Sel [3:0] $end
$var wire 5 0 address1 [4:0] $end
$var wire 5 1 address2 [4:0] $end
$var wire 5 2 address3 [4:0] $end
$var wire 5 3 address4 [4:0] $end
$var wire 1 ' clock $end
$var wire 1 ( en_write $end
$var wire 1 ) eval $end
$var wire 64 4 idata1 [63:0] $end
$var wire 64 5 idata2 [63:0] $end
$var wire 1 , read $end
$var wire 1 - reset $end
$var reg 64 6 ALU_Result [63:0] $end
$var reg 64 7 data [63:0] $end
$upscope $end
$upscope $end
$enddefinitions $end
#0
$dumpvars
bx 7
bx 6
bx 5
bx 4
bx 3
bx 2
bx 1
bx 0
bx /
b0 .
0-
x,
bx +
bx *
x)
x(
0'
bx &
bx %
bx $
bx #
bx "
bx !
$end
#5000
b1 .
1'
b1101111100001010011 +
b1101111100001010011 5
b1000 $
b1000 1
b110011010101010110010101 *
b110011010101010110010101 4
b1 #
b1 0
0,
0)
1(
#10000
b10 .
0'
#15000
b110011010101010110010101 !
b110011010101010110010101 7
b11 .
1'
b1 &
b1 3
1,
0(
#20000
b100 .
0'
#25000
b1101111100001010011 !
b1101111100001010011 7
b101 .
1'
b1000 &
b1000 3
#30000
b110 .
0'
#35000
b111 .
1'
#40000
b1000 .
0'
#45000
b110101000100110111101000 6
b1001 .
1'
b101 %
b101 2
b0 "
b0 /
0,
1)
#50000
b1010 .
0'
#55000
b1011 .
1'
#60000
b1100 .
0'
#65000
b110101000100110111101000 !
b110101000100110111101000 7
b1101 .
1'
b101 &
b101 3
1,
0)
#70000
b1110 .
0'
#75000
b110001100101110101000010 6
b1111 .
1'
b1111 %
b1111 2
b1 "
b1 /
0,
1)
#80000
b10000 .
0'
#85000
b10001 .
1'
#90000
b10010 .
0'
#95000
b110001100101110101000010 !
b110001100101110101000010 7
b10011 .
1'
b1111 &
b1111 3
1,
0)
#100000
b10100 .
0'
#105000
b1011001011100101110111110010001011101001111 6
b10101 .
1'
b10000 %
b10000 2
b10 "
b10 /
0,
1)
#110000
b10110 .
0'
#115000
b10111 .
1'
#120000
b11000 .
0'
#125000
b1011001011100101110111110010001011101001111 !
b1011001011100101110111110010001011101001111 7
b11001 .
1'
b10000 &
b10000 3
1,
0)
#130000
b11010 .
0'
#135000
b11101 6
b11011 .
1'
b10001 %
b10001 2
b11 "
b11 /
0,
1)
#140000
b11100 .
0'
#145000
b11101 .
1'
#150000
b11110 .
0'
#155000
b11101 !
b11101 7
b11111 .
1'
b10001 &
b10001 3
1,
0)
#160000
b100000 .
0'
#165000
b1100110101010101100101010 6
b100001 .
1'
b10010 %
b10010 2
b100 "
b100 /
0,
1)
#170000
b100010 .
0'
#175000
b100011 .
1'
#180000
b100100 .
0'
#185000
b1100110101010101100101010 !
b1100110101010101100101010 7
b100101 .
1'
b10010 &
b10010 3
1,
0)
#190000
b100110 .
0'
#195000
b11001101010101011001010 6
b100111 .
1'
b10011 %
b10011 2
b101 "
b101 /
0,
1)
#200000
b101000 .
0'
#205000
b101001 .
1'
#210000
b101010 .
0'
#215000
b11001101010101011001010 !
b11001101010101011001010 7
b101011 .
1'
b10011 &
b10011 3
1,
0)
#220000
b101100 .
0'
#225000
b1100110101010101100101010 6
b101101 .
1'
b10100 %
b10100 2
b110 "
b110 /
0,
1)
#230000
b101110 .
0'
#235000
b101111 .
1'
#240000
b110000 .
0'
#245000
b1100110101010101100101010 !
b1100110101010101100101010 7
b110001 .
1'
b10100 &
b10100 3
1,
0)
#250000
b110010 .
0'
#255000
b1000000000000000000000000000000000000000011001101010101011001010 6
b110011 .
1'
b10101 %
b10101 2
b111 "
b111 /
0,
1)
#260000
b110100 .
0'
#265000
b110101 .
1'
#270000
b110110 .
0'
#275000
b1000000000000000000000000000000000000000011001101010101011001010 !
b1000000000000000000000000000000000000000011001101010101011001010 7
b110111 .
1'
b10101 &
b10101 3
1,
0)
#280000
b111000 .
0'
#285000
b1000101000000010001 6
b111001 .
1'
b10110 %
b10110 2
b1000 "
b1000 /
0,
1)
#290000
b111010 .
0'
#295000
b111011 .
1'
#300000
b111100 .
0'
#305000
b1000101000000010001 !
b1000101000000010001 7
b111101 .
1'
b10110 &
b10110 3
1,
0)
#310000
b111110 .
0'
#315000
b110011111111110111010111 6
b111111 .
1'
b10111 %
b10111 2
b1001 "
b1001 /
0,
1)
#320000
b1000000 .
0'
#325000
b1000001 .
1'
#330000
b1000010 .
0'
#335000
b110011111111110111010111 !
b110011111111110111010111 7
b1000011 .
1'
b10111 &
b10111 3
1,
0)
#340000
b1000100 .
0'
#345000
b110010111010110111000110 6
b1000101 .
1'
b11000 %
b11000 2
b1010 "
b1010 /
0,
1)
#350000
b1000110 .
0'
#355000
b1000111 .
1'
#360000
b1001000 .
0'
#365000
b110010111010110111000110 !
b110010111010110111000110 7
b1001001 .
1'
b11000 &
b11000 3
1,
0)
#370000
b1001010 .
0'
#375000
b1111111111111111111111111111111111111111001100000000001000101000 6
b1001011 .
1'
b11001 %
b11001 2
b1011 "
b1011 /
0,
1)
#380000
b1001100 .
0'
#385000
b1001101 .
1'
#390000
b1001110 .
0'
#395000
b1111111111111111111111111111111111111111001100000000001000101000 !
b1111111111111111111111111111111111111111001100000000001000101000 7
b1001111 .
1'
b11001 &
b11001 3
1,
0)
#400000
b1010000 .
0'
#405000
b1111111111111111111111111111111111111111111110111010111111101110 6
b1010001 .
1'
b11010 %
b11010 2
b1100 "
b1100 /
0,
1)
#410000
b1010010 .
0'
#415000
b1010011 .
1'
#420000
b1010100 .
0'
#425000
b1111111111111111111111111111111111111111111110111010111111101110 !
b1111111111111111111111111111111111111111111110111010111111101110 7
b1010101 .
1'
b11010 &
b11010 3
1,
0)
#430000
b1010110 .
0'
#435000
b1111111111111111111111111111111111111111001101000101001000111001 6
b1010111 .
1'
b11011 %
b11011 2
b1101 "
b1101 /
0,
1)
#440000
b1011000 .
0'
#445000
b1011001 .
1'
#450000
b1011010 .
0'
#455000
b1111111111111111111111111111111111111111001101000101001000111001 !
b1111111111111111111111111111111111111111001101000101001000111001 7
b1011011 .
1'
b11011 &
b11011 3
1,
0)
#460000
b1011100 .
0'
#465000
b1 6
b1011101 .
1'
b11100 %
b11100 2
b1110 "
b1110 /
0,
1)
#470000
b1011110 .
0'
#475000
b1011111 .
1'
#480000
b1100000 .
0'
#485000
b1 !
b1 7
b1100001 .
1'
b11100 &
b11100 3
1,
0)
#490000
b1100010 .
0'
#495000
b0 6
b1100011 .
1'
b11101 %
b11101 2
b1111 "
b1111 /
0,
1)
#500000
b1100100 .
0'
#505000
b1100101 .
1'
#515000
b11101 &
b11101 3
1,
0)
