DDS/Assignment_3/4. Half Adder/halfadder.v
`timescale 1ns/1ns

module Half_Adder (
    input in_a, in_b,
    output sum, carry
);
    
    xor(sum, in_a, in_b);
    and(carry, in_a, in_b);

endmodule

module half_adder_tb;
    reg in_a = 1'b0;
    reg in_b = 1'b0;
    wire sum, carry;

    Half_Adder h1 (
        .in_a(in_a),
        .in_b(in_b),
        .sum(sum),
        .carry(carry)
    );


    initial
    begin
        $dumpfile("half_adder.vcd");
        $dumpvars(0, half_adder_tb);
    end

    initial
    begin
        in_a = 1'b0;
        in_b = 1'b0;
        #10;
        in_a = 1'b1;
        in_b = 1'b0;
        #10;
        in_a = 1'b0;
        in_b = 1'b1;
        #10;
        in_a = 1'b1;
        in_b = 1'b1;
        #10;
    end
    
    initial
    begin
        $monitor("A = %d\tB = %d\tSum = %d\tCarry = %d\t", in_a, in_b, sum, carry);
    end
endmodule

DDS/Assignment_3/5. Full Adder/fulladder.v
`timescale 1ns/1ns
`include "lib/halfadder.v"

module Full_Adder (
    input in_a, in_b, in_c,
    output sum, carry 
);
    wire x,y,z;
    Half_Adder h1(
        .in_a(in_a),
        .in_b(in_b),
        .sum(x),
        .carry(y)
    );

    Half_Adder h2(
        .in_a(x),
        .in_b(in_c),
        .sum(sum),
        .carry(z)
    );

    or(carry, z, y);

endmodule

module full_adder_tb;
    reg in_a = 1'b0;
    reg in_b = 1'b0;
    reg in_c = 1'b0;
    wire sum, carry;

    Full_Adder h1 (
        .in_a(in_a),
        .in_b(in_b),
        .in_c(in_c),
        .sum(sum),
        .carry(carry)
    );


    initial
    begin
        $dumpfile("full_adder.vcd");
        $dumpvars(0, full_adder_tb);
    end

    initial
    begin
        in_a = 1'b0;
        in_b = 1'b0;
        in_c = 1'b0;
        #10;
        in_a = 1'b0;
        in_b = 1'b0;
        in_c = 1'b1;
        #10;
        in_a = 1'b0;
        in_b = 1'b1;
        in_c = 1'b0;
        #10;
        in_a = 1'b0;
        in_b = 1'b1;
        in_c = 1'b1;
        #10;
        in_a = 1'b1;
        in_b = 1'b0;
        in_c = 1'b0;
        #10;
        in_a = 1'b1;
        in_b = 1'b0;
        in_c = 1'b1;
        #10;
        in_a = 1'b1;
        in_b = 1'b1;
        in_c = 1'b0;
        #10;
        in_a = 1'b1;
        in_b = 1'b1;
        in_c = 1'b1;
        #10;
    end
    
    initial
    begin
        $monitor("A = %d\tB = %d\tC = %d\tSum = %d\tCarry = %d\t", in_a, in_b, in_c, sum, carry);
    end
endmodule

DDS/Assignment_3/5. Full Adder/full_adder.vcd
$date
	Sat Oct 12 22:18:41 2019
$end
$version
	Icarus Verilog
$end
$timescale
	1ns
$end
$scope module full_adder_tb $end
$var wire 1 ! sum $end
$var wire 1 " carry $end
$var reg 1 # in_a $end
$var reg 1 $ in_b $end
$var reg 1 % in_c $end
$scope module h1 $end
$var wire 1 " carry $end
$var wire 1 # in_a $end
$var wire 1 $ in_b $end
$var wire 1 % in_c $end
$var wire 1 & z $end
$var wire 1 ' y $end
$var wire 1 ( x $end
$var wire 1 ! sum $end
$scope module h1 $end
$var wire 1 ' carry $end
$var wire 1 # in_a $end
$var wire 1 $ in_b $end
$var wire 1 ( sum $end
$upscope $end
$scope module h2 $end
$var wire 1 & carry $end
$var wire 1 ( in_a $end
$var wire 1 % in_b $end
$var wire 1 ! sum $end
$upscope $end
$upscope $end
$upscope $end
$scope module half_adder_tb $end
$var wire 1 ) sum $end
$var wire 1 * carry $end
$var reg 1 + in_a $end
$var reg 1 , in_b $end
$scope module h1 $end
$var wire 1 * carry $end
$var wire 1 + in_a $end
$var wire 1 , in_b $end
$var wire 1 ) sum $end
$upscope $end
$upscope $end
$enddefinitions $end
#0
$dumpvars
0,
0+
0*
0)
0(
0'
0&
0%
0$
0#
0"
0!
$end
#10
1)
1!
1+
1%
#20
1(
1,
0+
0%
1$
#30
1"
0)
1*
0!
1&
1+
1%
#40
0"
1!
0&
0%
0$
1#
#50
1"
0!
1&
1%
#60
0&
0(
1'
0%
1$
#70
1!
1%
