DDS/Assignment_3/9. 2-bit Multiplier/lib/HalfAdder.v
`timescale 1ns/1ns

module HA (input in_a, in_b,output Sum, Carry);
    
    and(Carry, in_a, in_b);
    xor(Sum, in_a, in_b);

endmodule

DDS/Assignment_3/9. 2-bit Multiplier/Multiplier.v
`timescale 1ns/1ns
`include "lib/HalfAdder.v"

module Multiplier (input a0, a1, b0, b1,output c0, c1, c2, c3);
    
    wire w,x,y,z;

    and(c0, a0, b0);
    and(x, a0, b1);
    and(y, a1, b0);
    HA h1 (x, y, c1, z);
    and(w, a1, b1);
    HA h2 (w, z, c2, c3);

    

endmodule 

module Multiplier_tb;

    reg a0 = 1'b0;
    reg b0 = 1'b0;
    reg a1 = 1'b0;
    reg b1 = 1'b0;

    wire c0, c1, c2, c3;

    Multiplier h1(a0,a1,b0,b1, c0, c1, c2, c3);

    initial
    begin
        $dumpfile("Multiplier.vcd");
        $dumpvars(0, Multiplier_tb);
    end

    initial
    begin
        a1 = 1'b0;
        a0 = 1'b0;
        b1 = 1'b0;
        b0 = 1'b0;
        #10;
        a1 = 1'b0;
        a0 = 1'b0;
        b1 = 1'b0;
        b0 = 1'b1;
        #10;
        a1 = 1'b0;
        a0 = 1'b0;
        b1 = 1'b1;
        b0 = 1'b0;
        #10;
        a1 = 1'b0;
        a0 = 1'b0;
        b1 = 1'b1;
        b0 = 1'b1;
        #10;
        a1 = 1'b0;
        a0 = 1'b1;
        b1 = 1'b0;
        b0 = 1'b0;
        #10;
        a1 = 1'b0;
        a0 = 1'b1;
        b1 = 1'b0;
        b0 = 1'b1;
        #10;
        a1 = 1'b0;
        a0 = 1'b1;
        b1 = 1'b1;
        b0 = 1'b0;
        #10;
        a1 = 1'b0;
        a0 = 1'b1;
        b1 = 1'b1;
        b0 = 1'b1;
        #10;
        a1 = 1'b1;
        a0 = 1'b0;
        b1 = 1'b0;
        b0 = 1'b0;
        #10;
        a1 = 1'b1;
        a0 = 1'b0;
        b1 = 1'b0;
        b0 = 1'b1;
        #10;
        a1 = 1'b1;
        a0 = 1'b0;
        b1 = 1'b1;
        b0 = 1'b0;
        #10;
        a1 = 1'b1;
        a0 = 1'b0;
        b1 = 1'b1;
        b0 = 1'b1;
        #10;
        a1 = 1'b1;
        a0 = 1'b1;
        b1 = 1'b0;
        b0 = 1'b0;
        #10;
        a1 = 1'b1;
        a0 = 1'b1;
        b1 = 1'b0;
        b0 = 1'b1;
        #10;
        a1 = 1'b1;
        a0 = 1'b1;
        b1 = 1'b1;
        b0 = 1'b1;
        #10;
    end

    initial
    begin
        $monitor("A1 = %d\tA2 = %d\tB1 = %d\tB0 = %d\t\tC3 = %d\tC2 = %d\tC1 = %d\tC0 = %d\t",a1,a0,b1,b0,c3,c2,c1,c0);
    end

endmodule

DDS/Assignment_3/9. 2-bit Multiplier/Multiplier.vcd
$date
	Sun Oct 13 00:05:50 2019
$end
$version
	Icarus Verilog
$end
$timescale
	1ns
$end
$scope module Multiplier_tb $end
$var wire 1 ! c3 $end
$var wire 1 " c2 $end
$var wire 1 # c1 $end
$var wire 1 $ c0 $end
$var reg 1 % a0 $end
$var reg 1 & a1 $end
$var reg 1 ' b0 $end
$var reg 1 ( b1 $end
$scope module h1 $end
$var wire 1 % a0 $end
$var wire 1 & a1 $end
$var wire 1 ' b0 $end
$var wire 1 ( b1 $end
$var wire 1 $ c0 $end
$var wire 1 ) w $end
$var wire 1 * x $end
$var wire 1 + y $end
$var wire 1 , z $end
$var wire 1 ! c3 $end
$var wire 1 " c2 $end
$var wire 1 # c1 $end
$scope module h1 $end
$var wire 1 , Carry $end
$var wire 1 # Sum $end
$var wire 1 * in_a $end
$var wire 1 + in_b $end
$upscope $end
$scope module h2 $end
$var wire 1 ! Carry $end
$var wire 1 " Sum $end
$var wire 1 ) in_a $end
$var wire 1 , in_b $end
$upscope $end
$upscope $end
$upscope $end
$enddefinitions $end
#0
$dumpvars
0,
0+
0*
0)
0(
0'
0&
0%
0$
0#
0"
0!
$end
#10
1'
#20
0'
1(
#30
1'
#40
0'
0(
1%
#50
1$
1'
#60
1#
0$
1*
0'
1(
#70
1$
1'
#80
0#
0$
0*
0'
0(
0%
1&
#90
1#
1+
1'
#100
0#
1"
0+
1)
0'
1(
#110
1#
1+
1'
#120
0#
0"
0+
0)
0'
0(
1%
#130
1#
1$
1+
1'
#140
1!
1,
0#
0"
1*
1)
1(
