DDS/Assignment_3/11. Code Converters/BinarytoGray/BinarytoGray.v
`timescale 1ns/1ns

module BinarytoGray (a, b, c, d, w, x, y, z);
    input a, b, c, d;
    output w, x ,y ,z;

    assign w = a;
    xor(x, a, b);
    xor(y, b, c);
    xor(z, c, d);
    

endmodule 

module BinarytoGray_tb;

    reg a = 1'b0;
    reg b = 1'b0;
    reg c = 1'b0;
    reg d = 1'b0;

    wire w, x, y, z;

    BinarytoGray h1(a,b,c,d,w,x,y,z);

    initial
    begin
        $dumpfile("BinarytoGray.vcd");
        $dumpvars(0, BinarytoGray_tb);
    end

    initial
    begin
        a = 1'b0;
        b = 1'b0;
        c = 1'b0;
        d = 1'b0;
        #10;
        a = 1'b0;
        b = 1'b0;
        c = 1'b0;
        d = 1'b1;
        #10;
        a = 1'b0;
        b = 1'b0;
        c = 1'b1;
        d = 1'b0;
        #10;
        a = 1'b0;
        b = 1'b0;
        c = 1'b1;
        d = 1'b1;
        #10;
        a = 1'b0;
        b = 1'b1;
        c = 1'b0;
        d = 1'b0;
        #10;
        a = 1'b0;
        b = 1'b1;
        c = 1'b0;
        d = 1'b1;
        #10;
        a = 1'b0;
        b = 1'b1;
        c = 1'b1;
        d = 1'b0;
        #10;
        a = 1'b0;
        b = 1'b1;
        c = 1'b1;
        d = 1'b1;
        #10;
        a = 1'b1;
        b = 1'b0;
        c = 1'b0;
        d = 1'b0;
        #10;
        a = 1'b1;
        b = 1'b0;
        c = 1'b0;
        d = 1'b1;
        #10;
        a = 1'b1;
        b = 1'b0;
        c = 1'b1;
        d = 1'b0;
        #10;
        a = 1'b1;
        b = 1'b0;
        c = 1'b1;
        d = 1'b1;
        #10;
        a = 1'b1;
        b = 1'b1;
        c = 1'b0;
        d = 1'b0;
        #10;
        a = 1'b1;
        b = 1'b1;
        c = 1'b0;
        d = 1'b1;
        #10;
        a = 1'b1;
        b = 1'b1;
        c = 1'b1;
        d = 1'b0;
        #10;
        a = 1'b1;
        b = 1'b1;
        c = 1'b1;
        d = 1'b1;
        #10;
    end

    initial
    begin
        $monitor("A = %d\tB = %d\tC = %d\tD = %d\t\tW = %d\tX = %d\tY = %d\tZ = %d\t",a,b,c,d,w,x,y,z);
    end

endmodule

DDS/Assignment_3/11. Code Converters/BinarytoGray/BinarytoGray.vcd
$date
	Sun Oct 13 00:17:12 2019
$end
$version
	Icarus Verilog
$end
$timescale
	1ns
$end
$scope module BinarytoGray_tb $end
$var wire 1 ! z $end
$var wire 1 " y $end
$var wire 1 # x $end
$var wire 1 $ w $end
$var reg 1 % a $end
$var reg 1 & b $end
$var reg 1 ' c $end
$var reg 1 ( d $end
$scope module h1 $end
$var wire 1 % a $end
$var wire 1 & b $end
$var wire 1 ' c $end
$var wire 1 ( d $end
$var wire 1 $ w $end
$var wire 1 # x $end
$var wire 1 " y $end
$var wire 1 ! z $end
$upscope $end
$upscope $end
$enddefinitions $end
#0
$dumpvars
0(
0'
0&
0%
0$
0#
0"
0!
$end
#10
1!
1(
#20
1"
0(
1'
#30
0!
1(
#40
1#
0(
0'
1&
#50
1!
1(
#60
0"
0(
1'
#70
0!
1(
#80
0(
0'
0&
1$
1%
#90
1!
1(
#100
1"
0(
1'
#110
0!
1(
#120
0#
0(
0'
1&
#130
1!
1(
#140
0"
0(
1'
#150
0!
1(
