DDS/Assignment_3/2. Universal Gates/3-input nor/nor.v
`timescale 1ns/1ns

module NOR (
    input in_a, in_b, in_c,
    output out 
);
    nor(out, in_a, in_b, in_c);    

endmodule

module NOR_tb;
    reg in_a = 1'b0;
    reg in_b = 1'b0;
    reg in_c = 1'b0;
    wire out;

    NOR h1 (
        .in_a(in_a),
        .in_b(in_b),
        .in_c(in_c),
        .out(out)
    );


    initial
    begin
        $dumpfile("nor.vcd");
        $dumpvars(0, NOR_tb);
    end

    initial
    begin
        in_a = 1'b0;
        in_b = 1'b0;
        in_c = 1'b0;
        #10;
        in_a = 1'b0;
        in_b = 1'b0;
        in_c = 1'b1;
        #10;
        in_a = 1'b0;
        in_b = 1'b1;
        in_c = 1'b0;
        #10;
        in_a = 1'b0;
        in_b = 1'b1;
        in_c = 1'b1;
        #10;
        in_a = 1'b1;
        in_b = 1'b0;
        in_c = 1'b0;
        #10;
        in_a = 1'b1;
        in_b = 1'b0;
        in_c = 1'b1;
        #10;
        in_a = 1'b1;
        in_b = 1'b1;
        in_c = 1'b0;
        #10;
        in_a = 1'b1;
        in_b = 1'b1;
        in_c = 1'b1;
        #10;
    end
    
    initial
    begin
        $monitor("A = %d\tB = %d\tC = %d\tNor = %d\t", in_a, in_b, in_c, out);
    end
endmodule

DDS/Assignment_3/2. Universal Gates/3-input nor/nor.vcd
$date
	Sat Oct 12 19:25:54 2019
$end
$version
	Icarus Verilog
$end
$timescale
	1ns
$end
$scope module NOR_tb $end
$var wire 1 ! out $end
$var reg 1 " in_a $end
$var reg 1 # in_b $end
$var reg 1 $ in_c $end
$scope module h1 $end
$var wire 1 " in_a $end
$var wire 1 # in_b $end
$var wire 1 $ in_c $end
$var wire 1 ! out $end
$upscope $end
$upscope $end
$enddefinitions $end
#0
$dumpvars
0$
0#
0"
1!
$end
#10
0!
1$
#20
0$
1#
#30
1$
#40
0$
0#
1"
#50
1$
#60
0$
1#
#70
1$
