DDS/Assignment_3/11. Code Converters/BCD to Excecss-3/BCDtoExcess3.v
`timescale 1ns/1ns

module BCDtoExcess3 (a, b, c, d, w, x, y, z);
    input a, b, c, d;
    output w, x ,y ,z;
    wire e,f;

    or(e,c,d);
    and(f,b,e);
    or(w,a,f);

    xor(x,b,e);

    not(z,d);

    xnor(y,c,d);
    

endmodule 

module BCDtoExcess3_tb;

    reg a = 1'b0;
    reg b = 1'b0;
    reg c = 1'b0;
    reg d = 1'b0;

    wire w, x, y, z;

    BCDtoExcess3 h1(a,b,c,d,w,x,y,z);

    initial
    begin
        $dumpfile("BCDtoExcess3.vcd");
        $dumpvars(0, BCDtoExcess3_tb);
    end

    initial
    begin
        a = 1'b0;
        b = 1'b0;
        c = 1'b0;
        d = 1'b0;
        #10;
        a = 1'b0;
        b = 1'b0;
        c = 1'b0;
        d = 1'b1;
        #10;
        a = 1'b0;
        b = 1'b0;
        c = 1'b1;
        d = 1'b0;
        #10;
        a = 1'b0;
        b = 1'b0;
        c = 1'b1;
        d = 1'b1;
        #10;
        a = 1'b0;
        b = 1'b1;
        c = 1'b0;
        d = 1'b0;
        #10;
        a = 1'b0;
        b = 1'b1;
        c = 1'b0;
        d = 1'b1;
        #10;
        a = 1'b0;
        b = 1'b1;
        c = 1'b1;
        d = 1'b0;
        #10;
        a = 1'b0;
        b = 1'b1;
        c = 1'b1;
        d = 1'b1;
        #10;
        a = 1'b1;
        b = 1'b0;
        c = 1'b0;
        d = 1'b0;
        #10;
        a = 1'b1;
        b = 1'b0;
        c = 1'b0;
        d = 1'b1;
        #10;
    end

    initial
    begin
        $monitor("A = %d\tB = %d\tC = %d\tD = %d\t\tW = %d\tX = %d\tY = %d\tZ = %d\t",a,b,c,d,w,x,y,z);
    end

endmodule

DDS/Assignment_3/11. Code Converters/BCD to Excecss-3/BCDtoExcess3.vcd
$date
	Sun Oct 13 00:14:22 2019
$end
$version
	Icarus Verilog
$end
$timescale
	1ns
$end
$scope module BCDtoExcess3_tb $end
$var wire 1 ! z $end
$var wire 1 " y $end
$var wire 1 # x $end
$var wire 1 $ w $end
$var reg 1 % a $end
$var reg 1 & b $end
$var reg 1 ' c $end
$var reg 1 ( d $end
$scope module h1 $end
$var wire 1 % a $end
$var wire 1 & b $end
$var wire 1 ' c $end
$var wire 1 ( d $end
$var wire 1 ) e $end
$var wire 1 * f $end
$var wire 1 $ w $end
$var wire 1 # x $end
$var wire 1 " y $end
$var wire 1 ! z $end
$upscope $end
$upscope $end
$enddefinitions $end
#0
$dumpvars
0*
0)
0(
0'
0&
0%
0$
0#
1"
1!
$end
#10
1#
1)
0!
0"
1(
#20
1!
0(
1'
#30
0!
1"
1(
#40
0$
1!
0)
0*
1#
0(
0'
1&
#50
1$
1*
0#
1)
0!
0"
1(
#60
1!
0(
1'
#70
0!
1"
1(
#80
1!
0)
0*
0#
0(
0'
0&
1%
#90
1#
1)
0!
0"
1(
